job_manager/__init__.py
job_manager/jobs.py
job_manager/templates/job_manager/_component_job_macro.html
job_manager/templates/job_manager/_component_job_style.html
job_manager/templates/job_manager/index.html
job_manager/templates/job_manager/login.html
flask_job_manager-0.2.0.dist-info/METADATA
flask_job_manager-0.2.0.dist-info/WHEEL
flask_job_manager-0.2.0.dist-info/top_level.txt
flask_job_manager-0.2.0.dist-info/RECORD
