Metadata-Version: 2.1
Name: flask-job-manager
Version: 0.2.0
Summary: pacote de gerenciamento de jobs para flask
Home-page: https://github.com/feiticeiro-tec/flask-JobManager
Author: Silvio Henrique Cruz Da Silva
Author-email: silviohenriquecruzdasilva@gmail.com
License: BSD3
Keywords: python,feiticeiro-tec,flask
Platform: UNKNOWN
Requires-Dist: loguru
